VectorUtils/Vector.py
VectorUtils/__init__.py
VectorUtils-1.3.5.dist-info/LICENSE
VectorUtils-1.3.5.dist-info/METADATA
VectorUtils-1.3.5.dist-info/WHEEL
VectorUtils-1.3.5.dist-info/top_level.txt
VectorUtils-1.3.5.dist-info/RECORD
