Metadata-Version: 2.1
Name: VectorUtils
Version: 1.3.5
Summary: Some Vector utils...
Home-page: UNKNOWN
Author: Monkvy
Author-email: moluecke@gmx.de
License: UNKNOWN
Keywords: python,physics,vector,2d,3d
Platform: UNKNOWN
Classifier: Intended Audience :: Developers
Classifier: Programming Language :: Python :: 3
Classifier: Operating System :: Unix
Classifier: Operating System :: MacOS :: MacOS X
Classifier: Operating System :: Microsoft :: Windows
License-File: LICENSE
